wea/__init__.py
wea/interface.py
wea/meta_data.py
wea/utils.py
wea/buffered_memory/__init__.py
wea/buffered_memory/buffered_exchange_array.py
wea/shared_memory/__init__.py
wea/shared_memory/shared_exchange_array.py
wea-0.1.3.dist-info/LICENSE
wea-0.1.3.dist-info/METADATA
wea-0.1.3.dist-info/WHEEL
wea-0.1.3.dist-info/top_level.txt
wea-0.1.3.dist-info/RECORD
