Metadata-Version: 2.1
Name: wea
Version: 0.1.3
Summary: The Wrapped Exchange Array is a convenient way in order to exchange array data easily via processes or remote nodes
Home-page: https://github.com/casabre/wea.py
Author: Carsten Sauerbrey
Author-email: carsten.sauerbrey@gmail.com
Maintainer: Carsten Sauerbrey
Maintainer-email: carsten.sauerbrey@gmail.com
License: MIT
Keywords: utility,data,array,exchange
Platform: Unix
Platform: Linux
Platform: Windows
Classifier: Development Status :: 4 - Beta
Classifier: Programming Language :: Python :: 3
Classifier: License :: OSI Approved :: MIT License
Classifier: Operating System :: OS Independent
Requires-Python: >=3.8
Requires-Dist: numpy (>=1.19.3)
Provides-Extra: docs
Requires-Dist: myst-parser ; extra == 'docs'
Requires-Dist: sphinx ; extra == 'docs'
Requires-Dist: sphinx-rtd-theme ; extra == 'docs'
Provides-Extra: test
Requires-Dist: coverage[toml] ; extra == 'test'
Requires-Dist: julia ; extra == 'test'
Requires-Dist: parameterized ; extra == 'test'
Requires-Dist: pytest ; extra == 'test'
Requires-Dist: pytest-cov ; extra == 'test'
